dp_packaging_index_server/__init__.py
dp_packaging_index_server/apps.py
dp_packaging_index_server/helper.py
dp_packaging_index_server/middleware.py
dp_packaging_index_server/models.py
dp_packaging_index_server/tests.py
dp_packaging_index_server/urls.py
dp_packaging_index_server/views.py
dp_packaging_index_server/management/__init__.py
dp_packaging_index_server/management/commands/__init__.py
dp_packaging_index_server/management/commands/cleanup.py
dp_packaging_index_server/management/commands/dp_packaging_index_server.py
dp_packaging_index_server/migrations/0001_initial.py
dp_packaging_index_server/migrations/__init__.py
dp_packaging_index_server-0.0.2.dist-info/LICENSE
dp_packaging_index_server-0.0.2.dist-info/METADATA
dp_packaging_index_server-0.0.2.dist-info/WHEEL
dp_packaging_index_server-0.0.2.dist-info/top_level.txt
dp_packaging_index_server-0.0.2.dist-info/RECORD
